keepa_crawler/__init__.py
keepa_crawler/client.py
keepa_crawler-1.0.0.dist-info/METADATA
keepa_crawler-1.0.0.dist-info/WHEEL
keepa_crawler-1.0.0.dist-info/top_level.txt
keepa_crawler-1.0.0.dist-info/RECORD
