Metadata-Version: 2.2
Name: keepa_crawler
Version: 1.0.0
Summary: A client to crawl Keepa's historical Amazon product data
Home-page: https://github.com/stanvanrooy/keepa_crawler
Author: Stan van Rooy
Author-email: stanvanrooy6@gmail.com
Classifier: Programming Language :: Python :: 3
Classifier: License :: OSI Approved :: MIT License
Classifier: Operating System :: OS Independent
Requires-Python: >=3.7
Requires-Dist: curl-cffi>=0.5.8
Dynamic: author
Dynamic: author-email
Dynamic: classifier
Dynamic: description
Dynamic: description-content-type
Dynamic: home-page
Dynamic: requires-dist
Dynamic: requires-python
Dynamic: summary
